package_Chongjun_Li/pmm.py
package_Chongjun_Li/.idea/.gitignore
package_Chongjun_Li/.idea/misc.xml
package_Chongjun_Li/.idea/modules.xml
package_Chongjun_Li/.idea/package_Chongjun_Li.iml
package_Chongjun_Li/.idea/workspace.xml
package_Chongjun_Li/.idea/inspectionProfiles/profiles_settings.xml
package_chongjun_li-0.0.1.dist-info/METADATA
package_chongjun_li-0.0.1.dist-info/WHEEL
package_chongjun_li-0.0.1.dist-info/licenses/LICENSE
package_chongjun_li-0.0.1.dist-info/RECORD
