Metadata-Version: 2.3
Name: package_Chongjun_Li
Version: 0.0.1
Summary: Predictive Mean Matching (nearest neighbour)
Project-URL: Homepage, https://github.com/pypa/sampleproject
Project-URL: Issues, https://github.com/pypa/sampleproject/issues
Author-email: Chongjun Li <cho.li@outlook.com>
License-File: LICENSE
Classifier: License :: OSI Approved :: MIT License
Classifier: Operating System :: OS Independent
Classifier: Programming Language :: Python :: 3
Requires-Python: >=3.8
